front/__init__.py
front/forms.py
front/models.py
front/urls.py
front/views.py
front/conf/__init__.py
front/conf/settings.py
front/migrations/0001_initial.py
front/migrations/0002_auto_20150123_0219.py
front/migrations/0003_auto_20170923_1427.py
front/migrations/__init__.py
front/south_migrations/0001_initial.py
front/south_migrations/0002_auto__add_placeholderhistory.py
front/south_migrations/__init__.py
front/static/epiceditor/images/edit.png
front/static/epiceditor/images/fullscreen.png
front/static/epiceditor/images/preview.png
front/static/epiceditor/images/modules/pulls/dirty-shade.png
front/static/epiceditor/js/epiceditor.js
front/static/epiceditor/js/epiceditor.min.js
front/static/epiceditor/themes/base/epiceditor.css
front/static/epiceditor/themes/editor/epic-dark.css
front/static/epiceditor/themes/editor/epic-light.css
front/static/epiceditor/themes/preview/bartik.css
front/static/epiceditor/themes/preview/github.css
front/static/epiceditor/themes/preview/preview-dark.css
front/static/front/css/front-edit.css
front/static/front/js/front-edit.ace-local.js
front/static/front/js/front-edit.ace.js
front/static/front/js/front-edit.ckeditor.js
front/static/front/js/front-edit.default.js
front/static/front/js/front-edit.epiceditor.js
front/static/front/js/front-edit.froala.js
front/static/front/js/front-edit.js
front/static/front/js/front-edit.medium.js
front/static/front/js/front-edit.redactor.js
front/static/front/js/front-edit.summernote.js
front/static/front/js/front-edit.wymeditor.js
front/static/to-markdown/to-markdown.js
front/static/wym/wymeditor_icon.png
front/static/wym/django/icons.png
front/static/wym/django/skin.css
front/static/wym/django/skin.js
front/templatetags/__init__.py
front/templatetags/front_tags.py
front/tests/__init__.py
front/tests/tests.py
front/tests/urls.py
front/tests/urls_no_save.py
front/tests/views.py
django_front-0.6.0.dist-info/LICENSE
django_front-0.6.0.dist-info/METADATA
django_front-0.6.0.dist-info/WHEEL
django_front-0.6.0.dist-info/top_level.txt
django_front-0.6.0.dist-info/RECORD
