Metadata-Version: 2.1
Name: django-front
Version: 0.6.0
Summary: A Django application to allow of front-end editing
Home-page: https://github.com/mbi/django-front
Author: Marco Bonetti
Author-email: mbonetti@gmail.com
License: MIT
Classifier: Development Status :: 4 - Beta
Classifier: Environment :: Web Environment
Classifier: Intended Audience :: Developers
Classifier: License :: OSI Approved :: MIT License
Classifier: Operating System :: OS Independent
Classifier: Programming Language :: Python
Classifier: Framework :: Django
Classifier: Framework :: Django :: 4.2
Classifier: Framework :: Django :: 5.0
Classifier: Programming Language :: Python :: 3.9
Classifier: Programming Language :: Python :: 3.10
Classifier: Programming Language :: Python :: 3.11
Classifier: Programming Language :: Python :: 3.12
License-File: LICENSE
Requires-Dist: django-classy-tags >=1.0
Requires-Dist: Django >=4.2
Requires-Dist: six
